[
    {
      "title": "Music Notifier",
      "description": "A mobile app that will send you notifications whenever a concert is playing in your area."
    },
    {
      "title": "The Ultimate Tech",
      "description": "Computers are the best equipment to have in the tech field. A computer can let you do almost everything in the tech world."
    },
    {
      "title": "Roll 'Em Up",
      "description": "A game for Windows and macOS where players move a ball through a series of increasingly challenging mazes."
    }
  ]